open_xiaoai_server-0.1.0.dist-info/METADATA
open_xiaoai_server-0.1.0.dist-info/WHEEL
open_xiaoai_server/__init__.py
open_xiaoai_server/open_xiaoai_server.abi3.so
open_xiaoai_server-0.1.0.dist-info/RECORD
