Metadata-Version: 2.4
Name: open_xiaoai_server
Version: 0.1.0
Classifier: Programming Language :: Rust
Classifier: Programming Language :: Python :: Implementation :: CPython
Classifier: Programming Language :: Python :: Implementation :: PyPy
Summary: Rust library for Python plugin
Requires-Python: >=3.8
